largest_remainder/__init__.py
largest_remainder/largest_remainder.py
largest_remainder/py.typed
largest_remainder-0.1.0.dist-info/licenses/LICENSE
largest_remainder-0.1.0.dist-info/METADATA
largest_remainder-0.1.0.dist-info/WHEEL
largest_remainder-0.1.0.dist-info/top_level.txt
largest_remainder-0.1.0.dist-info/RECORD
