Metadata-Version: 2.4
Name: largest-remainder
Version: 0.1.0
Summary: Largest Remainder (Hamilton method) algorithm for rounding values while preserving the total.
Author-email: Trustfull Engineering Team <engineering@trustfull.com>
License: MIT License
Project-URL: Homepage, https://github.com/fido-id/largest-remainder-py
Project-URL: Documentation, https://github.com/fido-id/largest-remainder-py#readme
Project-URL: Changelog, https://github.com/fido-id/largest-remainder-py/releases
Project-URL: Issues, https://github.com/fido-id/largest-remainder-py/issues
Keywords: largest remainder,hamilton method,rounding,quota
Classifier: Programming Language :: Python :: 3
Classifier: License :: OSI Approved :: MIT License
Classifier: Operating System :: OS Independent
Requires-Python: >=3.9
License-File: LICENSE
Dynamic: license-file
